yahykader_first_package/__init__.py
yahykader_first_package/main.py
yahykader_first_package-0.1.0.dist-info/METADATA
yahykader_first_package-0.1.0.dist-info/WHEEL
yahykader_first_package-0.1.0.dist-info/entry_points.txt
yahykader_first_package-0.1.0.dist-info/top_level.txt
yahykader_first_package-0.1.0.dist-info/RECORD
